pyNAVIS/__init__.py
pyNAVIS/dataset_gen.py
pyNAVIS/functions.py
pyNAVIS/generators.py
pyNAVIS/loaders.py
pyNAVIS/main_settings.py
pyNAVIS/objects.py
pyNAVIS/plots.py
pyNAVIS/report_functions.py
pyNAVIS/savers.py
pyNAVIS/splitters.py
pyNAVIS/utils.py
pynavis-1.2.5.dist-info/METADATA
pynavis-1.2.5.dist-info/WHEEL
pynavis-1.2.5.dist-info/top_level.txt
pynavis-1.2.5.dist-info/RECORD
