Metadata-Version: 2.4
Name: pyNAVIS
Version: 1.2.5
Summary: Useful tools to analyze and process spiking information from neuromorphic auditory sensors.
Home-page: https://github.com/jpdominguez/pyNAVIS
Download-URL: https://pypi.org/project/pyNAVIS/
Author: Juan P. Dominguez-Morales
Author-email: jpdominguez@us.es
License: GPL
Keywords: pyNAVIS,NAVIS,neuromorphic engineering,neuromorphic audio processing,neuromorphic sensors
Requires-Dist: matplotlib
Requires-Dist: numpy
Requires-Dist: scipy
Dynamic: author
Dynamic: author-email
Dynamic: description
Dynamic: description-content-type
Dynamic: download-url
Dynamic: home-page
Dynamic: keywords
Dynamic: license
Dynamic: requires-dist
Dynamic: summary
